setup.cfg
setup.py
python_shopify.egg-info/PKG-INFO
python_shopify.egg-info/SOURCES.txt
python_shopify.egg-info/dependency_links.txt
python_shopify.egg-info/requires.txt
python_shopify.egg-info/top_level.txt
shopify/__init__.py
shopify/base.py
shopify/fulfillments/__init__.py
shopify/fulfillments/api_wrapper.py
shopify/fulfillments/objects/__init__.py
shopify/fulfillments/objects/fulfillment.py
shopify/orders/__init__.py
shopify/orders/api_wrapper.py
shopify/orders/objects/__init__.py
shopify/orders/objects/address.py
shopify/orders/objects/client_detail.py
shopify/orders/objects/customer.py
shopify/orders/objects/discount_code.py
shopify/orders/objects/line_item.py
shopify/orders/objects/note_attribute.py
shopify/orders/objects/order.py
shopify/orders/objects/payment_detail.py
shopify/orders/objects/refund.py
shopify/orders/objects/shipping_line.py
shopify/orders/objects/tax_line.py
shopify/orders/objects/transaction.py
shopify/orders/tests/__init__.py
shopify/orders/tests/test_address.py
shopify/orders/tests/test_all.py
shopify/orders/tests/test_clientDetail.py
shopify/orders/tests/test_customer.py
shopify/orders/tests/test_lineItem.py
shopify/orders/tests/test_order.py
shopify/orders/tests/test_paymentDetail.py
shopify/orders/tests/test_shippingLine.py
shopify/orders/tests/test_taxLine.py
shopify/products/__init__.py
shopify/products/api_wrapper.py
shopify/products/objects/__init__.py
shopify/products/objects/image.py
shopify/products/objects/option.py
shopify/products/objects/product.py
shopify/products/objects/variant.py
shopify/products/tests/__init__.py
shopify/products/tests/test_all.py
shopify/products/tests/test_image.py
shopify/products/tests/test_option.py
shopify/products/tests/test_product.py
shopify/products/tests/test_variant.py