Metadata-Version: 1.0
Name: python-shopify
Version: 0.1.2
Summary: Wrapper and parser modules for Shopify's API.
Home-page: https://github.com/rochacbruno/python-shopify-api
Author: Bruno Rocha & Mark Sanders
Author-email: rochacbruno@gmail.com
License: LICENSE.txt
Platform: UNKNOWN
